<gbx version="6" unknown="R" class="0900D000" complvl="1">
	<body>
		<chunk class="0900C000" id="000">
			<node />
		</chunk>
		<chunk class="0900C000" id="001">
			<int32>1</int32>
		</chunk>
		<chunk class="0900D000" id="002">
			<int32>2</int32>
			<int32>12</int32>
			<vec3>4646.05419921875 8.0 512.0</vec3>
			<vec3>3267.174560546875 8.0 3269.760009765625</vec3>
			<vec3>3267.174560546875 8.0 -2245.760009765625</vec3>
			<vec3>1024.0 8.0 0.0</vec3>
			<vec3>1024.0 8.0 1024.0</vec3>
			<vec3>509.4145202636719 8.0 -3624.64013671875</vec3>
			<vec3>509.4145202636719 8.0 4648.64013671875</vec3>
			<vec3>0.0 8.0 0.0</vec3>
			<vec3>0.0 8.0 1024.0</vec3>
			<vec3>-2248.345458984375 8.0 -2245.760009765625</vec3>
			<vec3>-2248.345458984375 8.0 3269.760009765625</vec3>
			<vec3>-3594.3251953125 8.0 512.0</vec3>
			<int32>12</int32>
			<vec4>0.0 1.0 0.0 -8.0</vec4>
			<int32>7</int32>
			<int32>5</int32>
			<int32>9</int32>
			<int16>20</int16>
			<int8>0</int8>
			<int8>0</int8>
			<vec4>0.0 1.0 0.0 -8.0</vec4>
			<int32>5</int32>
			<int32>7</int32>
			<int32>3</int32>
			<int16>20</int16>
			<int8>0</int8>
			<int8>0</int8>
			<vec4>0.0 1.0 0.0 -8.0</vec4>
			<int32>11</int32>
			<int32>10</int32>
			<int32>8</int32>
			<int16>20</int16>
			<int8>0</int8>
			<int8>0</int8>
			<vec4>0.0 1.0 0.0 -8.0</vec4>
			<int32>6</int32>
			<int32>1</int32>
			<int32>4</int32>
			<int16>20</int16>
			<int8>0</int8>
			<int8>0</int8>
			<vec4>0.0 1.0 0.0 -8.0</vec4>
			<int32>0</int32>
			<int32>2</int32>
			<int32>3</int32>
			<int16>20</int16>
			<int8>0</int8>
			<int8>0</int8>
			<vec4>0.0 1.0 0.0 -8.0</vec4>
			<int32>3</int32>
			<int32>2</int32>
			<int32>5</int32>
			<int16>20</int16>
			<int8>0</int8>
			<int8>0</int8>
			<vec4>0.0 1.0 0.0 -8.0</vec4>
			<int32>4</int32>
			<int32>1</int32>
			<int32>0</int32>
			<int16>20</int16>
			<int8>0</int8>
			<int8>0</int8>
			<vec4>0.0 0.9999999403953552 0.0 -7.999999523162842</vec4>
			<int32>0</int32>
			<int32>3</int32>
			<int32>4</int32>
			<int16>20</int16>
			<int8>0</int8>
			<int8>0</int8>
			<vec4>0.0 1.0 0.0 -8.0</vec4>
			<int32>8</int32>
			<int32>10</int32>
			<int32>6</int32>
			<int16>20</int16>
			<int8>0</int8>
			<int8>0</int8>
			<vec4>0.0 1.0 0.0 -8.0</vec4>
			<int32>6</int32>
			<int32>4</int32>
			<int32>8</int32>
			<int16>20</int16>
			<int8>0</int8>
			<int8>0</int8>
			<vec4>0.0 1.0 0.0 -8.0</vec4>
			<int32>7</int32>
			<int32>9</int32>
			<int32>11</int32>
			<int16>20</int16>
			<int8>0</int8>
			<int8>0</int8>
			<vec4>0.0 1.0 0.0 -8.0</vec4>
			<int32>11</int32>
			<int32>8</int32>
			<int32>7</int32>
			<int16>20</int16>
			<int8>0</int8>
			<int8>0</int8>
			<int32>2</int32>
			<int32>20</int32>
			<int32>20</int32>
			<vec3>525.8642578125 8.0 512.0</vec3>
			<vec3>4120.189453125 0.0 4136.64013671875</vec3>
			<int32>-1</int32>
			<int32>8</int32>
			<vec3>525.8643798828125 8.0 -1556.320068359375</vec3>
			<vec3>4120.189453125 0.0 2068.320068359375</vec3>
			<int32>-1</int32>
			<int32>3</int32>
			<vec3>-1542.455322265625 8.0 -1556.320068359375</vec3>
			<vec3>2051.869873046875 0.0 2068.320068359375</vec3>
			<int32>-1</int32>
			<int32>1</int32>
			<vec3>-869.4654541015625 8.0 -1812.320068359375</vec3>
			<vec3>1378.8800048828125 0.0 1812.320068359375</vec3>
			<int32>0</int32>
			<int32>1</int32>
			<vec3>-1797.16259765625 8.0 -866.8800048828125</vec3>
			<vec3>1797.16259765625 0.0 1378.8800048828125</vec3>
			<int32>10</int32>
			<int32>1</int32>
			<vec3>2835.027099609375 8.0 -866.8800048828125</vec3>
			<vec3>1811.027099609375 0.0 1378.8800048828125</vec3>
			<int32>4</int32>
			<int32>3</int32>
			<vec3>1633.5872802734375 8.0 -1812.320068359375</vec3>
			<vec3>1633.5872802734375 0.0 1812.320068359375</vec3>
			<int32>-1</int32>
			<int32>1</int32>
			<vec3>1888.2945556640625 8.0 -1812.320068359375</vec3>
			<vec3>1378.8800048828125 0.0 1812.320068359375</vec3>
			<int32>5</int32>
			<int32>1</int32>
			<vec3>512.0 8.0 -1812.320068359375</vec3>
			<vec3>512.0 0.0 1812.320068359375</vec3>
			<int32>1</int32>
			<int32>8</int32>
			<vec3>525.8642578125 8.0 2580.320068359375</vec3>
			<vec3>4120.189453125 0.0 2068.320068359375</vec3>
			<int32>-1</int32>
			<int32>3</int32>
			<vec3>-1542.455322265625 8.0 2580.320068359375</vec3>
			<vec3>2051.869873046875 0.0 2068.320068359375</vec3>
			<int32>-1</int32>
			<int32>1</int32>
			<vec3>-1797.16259765625 8.0 1890.8800048828125</vec3>
			<vec3>1797.16259765625 0.0 1378.8800048828125</vec3>
			<int32>2</int32>
			<int32>1</int32>
			<vec3>-869.4654541015625 8.0 2836.320068359375</vec3>
			<vec3>1378.8800048828125 0.0 1812.320068359375</vec3>
			<int32>8</int32>
			<int32>1</int32>
			<vec3>2835.027099609375 8.0 1890.8800048828125</vec3>
			<vec3>1811.027099609375 0.0 1378.8800048828125</vec3>
			<int32>6</int32>
			<int32>3</int32>
			<vec3>1633.5872802734375 8.0 2836.320068359375</vec3>
			<vec3>1633.5872802734375 0.0 1812.320068359375</vec3>
			<int32>-1</int32>
			<int32>1</int32>
			<vec3>512.0 8.0 2836.320068359375</vec3>
			<vec3>512.0 0.0 1812.320068359375</vec3>
			<int32>9</int32>
			<int32>1</int32>
			<vec3>1888.2945556640625 8.0 2836.320068359375</vec3>
			<vec3>1378.8800048828125 0.0 1812.320068359375</vec3>
			<int32>3</int32>
			<int32>3</int32>
			<vec3>525.864501953125 8.0 512.0</vec3>
			<vec3>4120.189453125 0.0 512.0</vec3>
			<int32>-1</int32>
			<int32>1</int32>
			<vec3>-1797.16259765625 8.0 512.0</vec3>
			<vec3>1797.16259765625 0.0 512.0</vec3>
			<int32>11</int32>
			<int32>1</int32>
			<vec3>2835.027099609375 8.0 512.0</vec3>
			<vec3>1811.027099609375 0.0 512.0</vec3>
			<int32>7</int32>
		</chunk>
	</body>
</gbx>